[
    {
        "name": "ExchangeRates",
        "address": "0x17148c65204c05efD3d75726edE110b8c6eb82cA",
        "decimals": 18,
        "chainId": 256
    },
    {
        "name": "ProxyActions",
        "address": "0xb5B08477cF24F25561a07452122A83177fbCC430",
        "decimals": 18,
        "chainId": 256
    },
    {
        "name": "ProxyToActions",
        "address": "0xb5B08477cF24F25561a07452122A83177fbCC430",
        "decimals": 18,
        "chainId": 256
    },
    {
        "name": "Collateral",
        "address": "",
        "decimals": 18,
        "chainId": 256
    },
    {
        "name": "CollateralState",
        "address": "",
        "decimals": 18,
        "chainId": 256
    },
    {
        "name": "ExchangeRates",
        "address": "0xC0C14c6653f3237AB877Ba1ddb20e14d5fcC8270",
        "decimals": 18,
        "chainId": 3
    },
    {
        "name": "ProxyActions",
        "address": "0xA82A0931981eAFaEf3792DC8F957796eD54aa3B7",
        "decimals": 18,
        "chainId": 3
    },
    {
        "name": "ProxyToActions",
        "address": "0xa7Ad449b8b3E521D55D0bdEd9349Cc1784C4cc96",
        "decimals": 18,
        "chainId": 3
    },
    {
        "name": "Collateral",
        "address": "",
        "decimals": 18,
        "chainId": 3
    },
    {
        "name": "CollateralState",
        "address": "",
        "decimals": 18,
        "chainId": 3
    }
,
    {
        "name": "ExchangeRates",
        "address": "0x1b07a00C476e0E1bD7306e7BA36d111C3670A309",
        "decimals": 18,
        "chainId": 4
    },
    {
        "name": "ProxyActions",
        "address": "0x00fb7365645f94283a0fB6384bed53c40501961A",
        "decimals": 18,
        "chainId": 4
    },
    {
        "name": "ProxyToActions",
        "address": "0x3cF2BF36f8849dA37F49f473AFCf2df8933E320D",
        "decimals": 18,
        "chainId": 4
    },
    {
        "name": "Collateral",
        "address": "",
        "decimals": 18,
        "chainId": 4
    },
    {
        "name": "CollateralState",
        "address": "",
        "decimals": 18,
        "chainId": 4
    },
    {
        "name": "ProxyVault",
        "address": "0x36d9c3bA67fa048Ba5138E7Ea8456958d81b1D48",
        "decimals": 18,
        "chainId": 4
    },
    {
        "name": "MasterChef",
        "address": "0xEF88AEB30483dbfB10E33E2995474890fb0737b4",
        "decimals": 18,
        "chainId": 4
    },
    {
        "name": "Synthetic",
        "address": "0x2901E8978e5061444F27955A84142e2F240Ede37",
        "decimals": 18,
        "chainId": 4
    },
    {
        "name": "Blackhole",
        "address": "0xE9B8e98256485f63fd72b128acFfb501716ab106",
        "decimals": 18,
        "chainId": 4
    }
]
